<?xml version="1.0" encoding="utf-8" ?><dwsync><file name="bodybg-black.jpg" server="ftp.personal.psu.edu/www/" local="3217190320" remote="11992287783" /><file name="bodybg-green.jpg" server="ftp.personal.psu.edu/www/" local="3217190362" remote="11992287783" /><file name="bodybg-orange.jpg" server="ftp.personal.psu.edu/www/" local="3217190380" remote="11992287784" /><file name="bodybg-purple.jpg" server="ftp.personal.psu.edu/www/" local="3217190396" remote="11992287784" /><file name="bodybg-red.jpg" server="ftp.personal.psu.edu/www/" local="3217190334" remote="11992287784" /><file name="menuhover-black.jpg" server="ftp.personal.psu.edu/www/" local="3217118962" remote="11992287784" /><file name="menuhover-green.jpg" server="ftp.personal.psu.edu/www/" local="3217118772" remote="11992287785" /><file name="menuhover-orange.jpg" server="ftp.personal.psu.edu/www/" local="3217118682" remote="11992287785" /><file name="menuhover-purple.jpg" server="ftp.personal.psu.edu/www/" local="3217119046" remote="11992287785" /><file name="menuhover-red.jpg" server="ftp.personal.psu.edu/www/" local="3217118860" remote="11992287786" /></dwsync>